[
  {
    "time": 1773063000,
    "open": 390.05,
    "high": 392.99,
    "low": 389.5,
    "close": 392.39,
    "volume": 1436149,
    "count": 9711,
    "vwap": 391.572
  },
  {
    "time": 1773063300,
    "open": 392.36,
    "high": 392.85,
    "low": 387.34,
    "close": 387.4,
    "volume": 1459017,
    "count": 12266,
    "vwap": 389.24
  },
  {
    "time": 1773063600,
    "open": 387.4,
    "high": 387.96,
    "low": 386.42,
    "close": 387.13,
    "volume": 1210411,
    "count": 11060,
    "vwap": 387.066
  },
  {
    "time": 1773063900,
    "open": 387.17,
    "high": 387.17,
    "low": 384.8,
    "close": 385.13,
    "volume": 1324448,
    "count": 11014,
    "vwap": 386.167
  },
  {
    "time": 1773064200,
    "open": 385.07,
    "high": 385.58,
    "low": 384.04,
    "close": 384.38,
    "volume": 1217554,
    "count": 9870,
    "vwap": 384.926
  },
  {
    "time": 1773064500,
    "open": 384.37,
    "high": 385.02,
    "low": 383.04,
    "close": 384.57,
    "volume": 1420833,
    "count": 11230,
    "vwap": 384.113
  },
  {
    "time": 1773064800,
    "open": 384.55,
    "high": 385.93,
    "low": 383.9,
    "close": 385.92,
    "volume": 1049747,
    "count": 8573,
    "vwap": 384.971
  },
  {
    "time": 1773065100,
    "open": 385.9,
    "high": 386.17,
    "low": 382.53,
    "close": 383.3,
    "volume": 1298328,
    "count": 10032,
    "vwap": 383.869
  },
  {
    "time": 1773065400,
    "open": 383.29,
    "high": 383.38,
    "low": 381.4,
    "close": 383.26,
    "volume": 1187042,
    "count": 10354,
    "vwap": 382.261
  },
  {
    "time": 1773065700,
    "open": 383.25,
    "high": 384.39,
    "low": 382.91,
    "close": 383.97,
    "volume": 852029,
    "count": 7586,
    "vwap": 383.666
  },
  {
    "time": 1773066000,
    "open": 383.94,
    "high": 385.09,
    "low": 382.42,
    "close": 384.8,
    "volume": 996495,
    "count": 8021,
    "vwap": 383.948
  },
  {
    "time": 1773066300,
    "open": 384.81,
    "high": 385.16,
    "low": 382.68,
    "close": 383.45,
    "volume": 748637,
    "count": 6252,
    "vwap": 383.784
  },
  {
    "time": 1773066600,
    "open": 383.45,
    "high": 384.47,
    "low": 383.44,
    "close": 384.15,
    "volume": 695177,
    "count": 5868,
    "vwap": 384.034
  },
  {
    "time": 1773066900,
    "open": 384.13,
    "high": 385.77,
    "low": 383.83,
    "close": 385.29,
    "volume": 877267,
    "count": 7252,
    "vwap": 384.907
  },
  {
    "time": 1773067200,
    "open": 385.28,
    "high": 385.63,
    "low": 384.37,
    "close": 385.57,
    "volume": 674288,
    "count": 5663,
    "vwap": 385.064
  },
  {
    "time": 1773067500,
    "open": 385.6,
    "high": 385.99,
    "low": 385.29,
    "close": 385.82,
    "volume": 721344,
    "count": 6237,
    "vwap": 385.635
  },
  {
    "time": 1773067800,
    "open": 385.8,
    "high": 386.31,
    "low": 385.38,
    "close": 386.06,
    "volume": 794647,
    "count": 6307,
    "vwap": 385.807
  },
  {
    "time": 1773068100,
    "open": 385.98,
    "high": 386.36,
    "low": 385.11,
    "close": 385.69,
    "volume": 697662,
    "count": 6067,
    "vwap": 385.846
  },
  {
    "time": 1773068400,
    "open": 385.7,
    "high": 387.12,
    "low": 385.7,
    "close": 386.56,
    "volume": 745965,
    "count": 6088,
    "vwap": 386.48
  },
  {
    "time": 1773068700,
    "open": 386.54,
    "high": 387.32,
    "low": 386.4,
    "close": 386.59,
    "volume": 546333,
    "count": 4884,
    "vwap": 386.972
  },
  {
    "time": 1773069000,
    "open": 386.58,
    "high": 387.37,
    "low": 386.24,
    "close": 387,
    "volume": 535817,
    "count": 4388,
    "vwap": 386.866
  },
  {
    "time": 1773069300,
    "open": 387.03,
    "high": 387.72,
    "low": 386.7,
    "close": 387,
    "volume": 584964,
    "count": 4815,
    "vwap": 387.291
  },
  {
    "time": 1773069600,
    "open": 386.98,
    "high": 387.99,
    "low": 386.52,
    "close": 387.69,
    "volume": 547598,
    "count": 4619,
    "vwap": 387.298
  },
  {
    "time": 1773069900,
    "open": 387.68,
    "high": 388.59,
    "low": 387.39,
    "close": 388.33,
    "volume": 546414,
    "count": 4628,
    "vwap": 388.102
  },
  {
    "time": 1773070200,
    "open": 388.23,
    "high": 388.35,
    "low": 387.55,
    "close": 387.94,
    "volume": 467473,
    "count": 4482,
    "vwap": 387.99
  },
  {
    "time": 1773070500,
    "open": 387.95,
    "high": 388.47,
    "low": 387.5,
    "close": 388.36,
    "volume": 476809,
    "count": 4499,
    "vwap": 388.012
  },
  {
    "time": 1773070800,
    "open": 388.31,
    "high": 388.34,
    "low": 387.17,
    "close": 387.5,
    "volume": 425069,
    "count": 3910,
    "vwap": 387.657
  },
  {
    "time": 1773071100,
    "open": 387.52,
    "high": 388.55,
    "low": 387.32,
    "close": 388.41,
    "volume": 433512,
    "count": 3496,
    "vwap": 388.148
  },
  {
    "time": 1773071400,
    "open": 388.46,
    "high": 389.79,
    "low": 388.35,
    "close": 389.5,
    "volume": 592565,
    "count": 4921,
    "vwap": 389.036
  },
  {
    "time": 1773071700,
    "open": 389.5,
    "high": 389.95,
    "low": 389.1,
    "close": 389.56,
    "volume": 522819,
    "count": 4249,
    "vwap": 389.544
  },
  {
    "time": 1773072000,
    "open": 389.58,
    "high": 390.01,
    "low": 389.13,
    "close": 389.76,
    "volume": 502884,
    "count": 3800,
    "vwap": 389.636
  },
  {
    "time": 1773072300,
    "open": 389.78,
    "high": 389.85,
    "low": 389.16,
    "close": 389.23,
    "volume": 381221,
    "count": 3512,
    "vwap": 389.508
  },
  {
    "time": 1773072600,
    "open": 389.22,
    "high": 389.41,
    "low": 388.52,
    "close": 389.1,
    "volume": 544251,
    "count": 4445,
    "vwap": 388.938
  },
  {
    "time": 1773072900,
    "open": 389.08,
    "high": 389.19,
    "low": 388.68,
    "close": 388.79,
    "volume": 296015,
    "count": 2567,
    "vwap": 388.896
  },
  {
    "time": 1773073200,
    "open": 388.81,
    "high": 389.21,
    "low": 388.2,
    "close": 389.09,
    "volume": 521285,
    "count": 4288,
    "vwap": 388.753
  },
  {
    "time": 1773073500,
    "open": 389.08,
    "high": 390.89,
    "low": 389.04,
    "close": 390.16,
    "volume": 696492,
    "count": 5602,
    "vwap": 390.222
  },
  {
    "time": 1773073800,
    "open": 390.16,
    "high": 390.28,
    "low": 389.23,
    "close": 390.09,
    "volume": 461324,
    "count": 3964,
    "vwap": 389.687
  },
  {
    "time": 1773074100,
    "open": 390.09,
    "high": 390.71,
    "low": 389.71,
    "close": 390.07,
    "volume": 468793,
    "count": 3833,
    "vwap": 390.177
  },
  {
    "time": 1773074400,
    "open": 390.1,
    "high": 390.88,
    "low": 389.78,
    "close": 390.65,
    "volume": 446082,
    "count": 3862,
    "vwap": 390.296
  },
  {
    "time": 1773074700,
    "open": 390.66,
    "high": 390.99,
    "low": 390.25,
    "close": 390.41,
    "volume": 395761,
    "count": 3370,
    "vwap": 390.685
  },
  {
    "time": 1773075000,
    "open": 390.4,
    "high": 390.68,
    "low": 390.07,
    "close": 390.3,
    "volume": 358668,
    "count": 3082,
    "vwap": 390.443
  },
  {
    "time": 1773075300,
    "open": 390.27,
    "high": 390.58,
    "low": 389.85,
    "close": 390.05,
    "volume": 403451,
    "count": 3690,
    "vwap": 390.191
  },
  {
    "time": 1773075600,
    "open": 390.07,
    "high": 390.63,
    "low": 389.71,
    "close": 390.08,
    "volume": 492074,
    "count": 4365,
    "vwap": 390.088
  },
  {
    "time": 1773075900,
    "open": 390.09,
    "high": 390.26,
    "low": 389.3,
    "close": 389.93,
    "volume": 379329,
    "count": 3407,
    "vwap": 389.803
  },
  {
    "time": 1773076200,
    "open": 389.94,
    "high": 390.4,
    "low": 389.8,
    "close": 390.18,
    "volume": 389559,
    "count": 3096,
    "vwap": 390.156
  },
  {
    "time": 1773076500,
    "open": 390.19,
    "high": 390.22,
    "low": 389.34,
    "close": 389.52,
    "volume": 320632,
    "count": 2659,
    "vwap": 389.778
  },
  {
    "time": 1773076800,
    "open": 389.52,
    "high": 389.57,
    "low": 388.68,
    "close": 389.19,
    "volume": 406218,
    "count": 3319,
    "vwap": 389.111
  },
  {
    "time": 1773077100,
    "open": 389.15,
    "high": 389.29,
    "low": 388.78,
    "close": 389.01,
    "volume": 333359,
    "count": 2800,
    "vwap": 389.03
  },
  {
    "time": 1773077400,
    "open": 389,
    "high": 389.88,
    "low": 388.92,
    "close": 389.27,
    "volume": 398675,
    "count": 3421,
    "vwap": 389.308
  },
  {
    "time": 1773077700,
    "open": 389.25,
    "high": 389.93,
    "low": 388.67,
    "close": 388.98,
    "volume": 460258,
    "count": 3664,
    "vwap": 389.256
  },
  {
    "time": 1773078000,
    "open": 388.94,
    "high": 389.4,
    "low": 388.51,
    "close": 388.99,
    "volume": 368258,
    "count": 3047,
    "vwap": 388.991
  },
  {
    "time": 1773078300,
    "open": 389.01,
    "high": 389.89,
    "low": 388.93,
    "close": 389.56,
    "volume": 296289,
    "count": 2484,
    "vwap": 389.484
  },
  {
    "time": 1773078600,
    "open": 389.54,
    "high": 390.15,
    "low": 389.17,
    "close": 389.99,
    "volume": 357196,
    "count": 3091,
    "vwap": 389.779
  },
  {
    "time": 1773078900,
    "open": 390.02,
    "high": 390.13,
    "low": 389.66,
    "close": 390.06,
    "volume": 251649,
    "count": 2196,
    "vwap": 389.939
  },
  {
    "time": 1773079200,
    "open": 390.08,
    "high": 390.61,
    "low": 389.66,
    "close": 389.83,
    "volume": 433724,
    "count": 3817,
    "vwap": 390.181
  },
  {
    "time": 1773079500,
    "open": 389.84,
    "high": 390.55,
    "low": 389.7,
    "close": 389.99,
    "volume": 353112,
    "count": 3217,
    "vwap": 390.054
  },
  {
    "time": 1773079800,
    "open": 389.95,
    "high": 390.89,
    "low": 389.82,
    "close": 390.79,
    "volume": 346231,
    "count": 2962,
    "vwap": 390.464
  },
  {
    "time": 1773080100,
    "open": 390.79,
    "high": 391.55,
    "low": 390.37,
    "close": 391.46,
    "volume": 497998,
    "count": 4381,
    "vwap": 391.149
  },
  {
    "time": 1773080400,
    "open": 391.43,
    "high": 391.77,
    "low": 390.88,
    "close": 391.49,
    "volume": 406885,
    "count": 3841,
    "vwap": 391.382
  },
  {
    "time": 1773080700,
    "open": 391.49,
    "high": 391.59,
    "low": 390.97,
    "close": 391.29,
    "volume": 290561,
    "count": 2587,
    "vwap": 391.309
  },
  {
    "time": 1773081000,
    "open": 391.27,
    "high": 392.17,
    "low": 391.05,
    "close": 392.17,
    "volume": 347368,
    "count": 3050,
    "vwap": 391.466
  },
  {
    "time": 1773081300,
    "open": 392.16,
    "high": 392.37,
    "low": 391.84,
    "close": 392.34,
    "volume": 473090,
    "count": 3936,
    "vwap": 392.166
  },
  {
    "time": 1773081600,
    "open": 392.35,
    "high": 393.06,
    "low": 392.17,
    "close": 392.48,
    "volume": 622833,
    "count": 5308,
    "vwap": 392.638
  },
  {
    "time": 1773081900,
    "open": 392.46,
    "high": 393.73,
    "low": 392.38,
    "close": 393.25,
    "volume": 618106,
    "count": 5090,
    "vwap": 393.196
  },
  {
    "time": 1773082200,
    "open": 393.25,
    "high": 393.3,
    "low": 392.69,
    "close": 392.82,
    "volume": 401277,
    "count": 3717,
    "vwap": 392.962
  },
  {
    "time": 1773082500,
    "open": 392.82,
    "high": 392.82,
    "low": 392.26,
    "close": 392.38,
    "volume": 441139,
    "count": 4260,
    "vwap": 392.489
  },
  {
    "time": 1773082800,
    "open": 392.36,
    "high": 392.67,
    "low": 392.07,
    "close": 392.53,
    "volume": 393203,
    "count": 3447,
    "vwap": 392.406
  },
  {
    "time": 1773083100,
    "open": 392.52,
    "high": 392.74,
    "low": 391.98,
    "close": 392.01,
    "volume": 425464,
    "count": 3792,
    "vwap": 392.426
  },
  {
    "time": 1773083400,
    "open": 392.01,
    "high": 392.74,
    "low": 391.7,
    "close": 392.4,
    "volume": 434701,
    "count": 3676,
    "vwap": 392.33
  },
  {
    "time": 1773083700,
    "open": 392.39,
    "high": 396.16,
    "low": 392.15,
    "close": 396,
    "volume": 965375,
    "count": 8003,
    "vwap": 393.962
  },
  {
    "time": 1773084000,
    "open": 395.99,
    "high": 397.91,
    "low": 395.34,
    "close": 397.6,
    "volume": 1333790,
    "count": 11838,
    "vwap": 396.888
  },
  {
    "time": 1773084300,
    "open": 397.61,
    "high": 400.7,
    "low": 397.11,
    "close": 400.6,
    "volume": 1385565,
    "count": 10750,
    "vwap": 399.183
  },
  {
    "time": 1773084600,
    "open": 400.56,
    "high": 400.75,
    "low": 398.74,
    "close": 400.11,
    "volume": 1110762,
    "count": 10137,
    "vwap": 399.778
  },
  {
    "time": 1773084900,
    "open": 400.11,
    "high": 401.59,
    "low": 399.33,
    "close": 400.93,
    "volume": 1063319,
    "count": 9565,
    "vwap": 400.529
  },
  {
    "time": 1773085200,
    "open": 400.91,
    "high": 400.91,
    "low": 398.6,
    "close": 399.45,
    "volume": 897440,
    "count": 8059,
    "vwap": 399.444
  },
  {
    "time": 1773085500,
    "open": 399.48,
    "high": 399.69,
    "low": 398.25,
    "close": 399.42,
    "volume": 685450,
    "count": 5788,
    "vwap": 399.032
  },
  {
    "time": 1773085800,
    "open": 399.4,
    "high": 399.75,
    "low": 397.66,
    "close": 397.79,
    "volume": 845671,
    "count": 7498,
    "vwap": 398.517
  },
  {
    "time": 1773086100,
    "open": 397.87,
    "high": 398.97,
    "low": 397.33,
    "close": 398.64,
    "volume": 1227524,
    "count": 13018,
    "vwap": 398.385
  }
]
